betterschema/__init__.py
betterschema/baselib.cpython-311-darwin.so
betterschema/core.py
betterschema/render.py
betterschema/old/__init__.py
betterschema/old/schema.py
betterschema-0.1.1.dist-info/METADATA
betterschema-0.1.1.dist-info/WHEEL
betterschema-0.1.1.dist-info/top_level.txt
betterschema-0.1.1.dist-info/RECORD
